Metadata-Version: 1.1
Name: hearhourtempmail
Version: 0.0.1
Summary: This for testing
Home-page: UNKNOWN
Author: HearHour
Author-email: hourfoto@gmail.com
License: MIT
Keywords: hearhourtempmail
Platform: UNKNOWN
Classifier: Development Status :: 5 - Production/Stable
Classifier: Intended Audience :: Education
Classifier: Operating System :: Microsoft :: Windows :: Windows 10
Classifier: License :: OSI Approved :: MIT License
Classifier: Programming Language :: Python :: 3
